[{"curr_city": "Волгоград", "Q2": "ЛюблинО", "year": "больше года", "city_father": "Красный Луч", "Q1": "ДУбны", "age": "51", "city": "Волгоград", "name": "Алексей", "Q3": "БалАшихе", "city_mother": "Тамбов"}, {"city": "Волгоград", "Q2": "ЛЮблино", "city_father": "Волгоград", "year": "больше года", "city_mother": "Баку", "age": "19", "Q1": "ДУбны", "name": "Виктория", "Q3": "БалАшихе", "curr_city": "Москва"}, {"curr_city": "Волгоград", "Q2": "ЛЮблино", "year": "больше года", "city_father": "Волгоград", "Q1": "ДУбны", "age": "16", "city": "Волгоград", "name": "Георгий", "Q3": "БалАшихе", "city_mother": "Баку"}, {"city": "Москва", "Q2": "ЛюблинО", "city_father": "Тамбов", "year": "больше года", "city_mother": "Тамбов", "age": "19", "Q1": "ДубнЫ", "name": "", "Q3": "БалАшихе", "curr_city": "Москва"}, {"curr_city": "Москва", "Q2": "ЛюблинО", "year": "больше года", "city_father": "Москва", "Q1": "ДубнЫ", "age": "19", "city": "Москва", "name": "", "Q3": "БалАшихе", "city_mother": "Москва"}, {"city": "Волгоград", "Q2": "ЛюблинО", "city_father": "", "year": "больше года", "city_mother": "", "age": "24", "Q1": "ДУбны", "name": "", "Q3": "БалАшихе", "curr_city": "Москва"}, {"curr_city": "Москва", "Q2": "ЛЮблино", "year": "больше года", "city_father": "", "Q1": "ДУбны", "age": "19", "city": "Челябинск", "name": "Анна", "Q3": "БалАшихе", "city_mother": ""}]